{
  "generated_at": "2026-07-16T16:20:00+08:00",
  "source": "zarazhangrui/frontend-slides",
  "integration_goal": "STYLE_PRESETS + bold-template-pack metadata strategy reuse for nichecraft html_deck",
  "stage_policy": {
    "design_canvas": {
      "width": 1920,
      "height": 1080
    },
    "scaling": "scale-to-viewport-or-fixed",
    "notes": [
      "Keep fixed 16:9 authored coordinates",
      "Stage should be scaled uniformly to viewport"
    ]
  },
  "selection_policy": {
    "strategy": [
      "Read selection-index metadata first and shortlist by mood/tone/formality/density.",
      "For a candidate deck choose 1 safe style + 1 bold option + 1 wildcard style.",
      "Do not bulk-read template design.md files before final shortlist."
    ],
    "selection_keys": [
      "mood",
      "tone",
      "best_for",
      "avoid_for",
      "formality",
      "density",
      "scheme"
    ]
  },
  "safe_style_presets": [
    {
      "title": "1. Bold Signal",
      "vibe": "Confident, bold, modern, high-impact",
      "layout": "Colored card on dark gradient. Number top-left, navigation top-right, title bottom-left."
    },
    {
      "title": "2. Electric Studio",
      "vibe": "Bold, clean, professional, high contrast",
      "layout": "Split panel—white top, blue bottom. Brand marks in corners."
    },
    {
      "title": "3. Creative Voltage",
      "vibe": "Bold, creative, energetic, retro-modern",
      "layout": "Split panels—electric blue left, dark right. Script accents."
    },
    {
      "title": "4. Dark Botanical",
      "vibe": "Elegant, sophisticated, artistic, premium",
      "layout": "Centered content on dark. Abstract soft shapes in corner."
    },
    {
      "title": "5. Notebook Tabs",
      "vibe": "Editorial, organized, elegant, tactile",
      "layout": "Cream paper card on dark background. Colorful tabs on right edge."
    },
    {
      "title": "6. Pastel Geometry",
      "vibe": "Friendly, organized, modern, approachable",
      "layout": "White card on pastel background. Vertical pills on right edge."
    },
    {
      "title": "7. Split Pastel",
      "vibe": "Playful, modern, friendly, creative",
      "layout": "Two-color vertical split (peach left, lavender right)."
    },
    {
      "title": "8. Vintage Editorial",
      "vibe": "Witty, confident, editorial, personality-driven",
      "layout": "Centered content on cream. Abstract geometric shapes as accent."
    },
    {
      "title": "9. Neon Cyber",
      "vibe": "Futuristic, techy, confident",
      "layout": ""
    },
    {
      "title": "10. Terminal Green",
      "vibe": "Developer-focused, hacker aesthetic",
      "layout": ""
    },
    {
      "title": "11. Swiss Modern",
      "vibe": "Clean, precise, Bauhaus-inspired",
      "layout": ""
    },
    {
      "title": "12. Paper & Ink",
      "vibe": "Editorial, literary, thoughtful",
      "layout": ""
    }
  ],
  "bold_pack_overlap_with_nichecraft": [
    {
      "slug": "block-frame",
      "name": "BlockFrame",
      "tagline": "Neobrutalist deck with pastel-neon color blocks and chunky black borders.",
      "mood": [
        "bold",
        "playful",
        "graphic",
        "fresh"
      ],
      "tone": [
        "confident",
        "graphic",
        "pop",
        "design-led"
      ],
      "formality": "medium-low",
      "density": "high",
      "scheme": "light",
      "best_for": "Anything that should feel pop-graphic and design-led: indie SaaS launches, agency credentials, creative reviews, brand redesigns. Also a strong unexpected pick for tech, finance, or research when the speaker wants to land as confident and contemporary rather than buttoned-up.",
      "avoid_for": "Contexts that require quiet institutional restraint or traditional weight (regulated disclosures, formal legal briefs).",
      "preview_md": "bold-template-pack/templates/block-frame/preview.md",
      "design_md": "bold-template-pack/templates/block-frame/design.md"
    },
    {
      "slug": "grove",
      "name": "Grove",
      "tagline": "Forest-green canvas with cream type, classical Playfair serifs, and a single rust accent.",
      "mood": [
        "organic",
        "considered",
        "warm",
        "literary",
        "natural"
      ],
      "tone": [
        "classical",
        "warm",
        "considered",
        "patient"
      ],
      "formality": "medium-high",
      "density": "medium",
      "scheme": "mixed",
      "best_for": "Anything that should feel organic, considered, and grown-up: sustainability and wellness brands, outdoor / nature products, wineries and restaurants, literary or arts decks, advisory deliverables, bilingual EN/CN reports. Also a calm, distinctive choice for tech, research, or business decks that want patience over urgency.",
      "avoid_for": "Decks that need neon energy or rapid-fire pop — the forest-green canvas and Playfair serif commit to a slow, classical voice.",
      "preview_md": "bold-template-pack/templates/grove/preview.md",
      "design_md": "bold-template-pack/templates/grove/design.md"
    },
    {
      "slug": "long-table",
      "name": "Long Table",
      "tagline": "Warm cream and rust-red supper-club aesthetic with bold uppercase grotesk headlines, Fraunces serifs, and pill-shaped outlined buttons.",
      "mood": [
        "warm",
        "intimate",
        "modern",
        "friendly",
        "small-batch",
        "social",
        "hospitality"
      ],
      "tone": [
        "warm",
        "playful",
        "considered",
        "social",
        "magazine-friendly",
        "modern-editorial"
      ],
      "formality": "medium",
      "density": "medium",
      "scheme": "light",
      "best_for": "Anything that should feel like a warm, intimate, modern hospitality / community brand: supper clubs, dinner series, small restaurants, creative-studio events, membership pitches, lifestyle and wine brands. Equally good for any deck wanting a single warm accent colour, mixed-weight typography, and a social-media-aware modern-editorial voice.",
      "avoid_for": "Decks that need corporate polish, technical density, or a cold / minimalist register — the rust-red palette and bold serif mix are intentionally warm and people-facing.",
      "preview_md": "bold-template-pack/templates/long-table/preview.md",
      "design_md": "bold-template-pack/templates/long-table/design.md"
    },
    {
      "slug": "monochrome",
      "name": "Monochrome",
      "tagline": "Ivory ledger paper with all-black type; Lora serif headlines, Jost body, no color at all.",
      "mood": [
        "restrained",
        "literary",
        "archival",
        "ledger"
      ],
      "tone": [
        "literary",
        "considered",
        "neutral",
        "honest"
      ],
      "formality": "high",
      "density": "high",
      "scheme": "light",
      "best_for": "Anything that should feel like a hand-typeset ledger: user research synthesis, white papers, longform reports, academic and policy briefs, advisory deliverables, bilingual EN/CN reports. Equally good for tech, design, or brand decks that want their words to be the only thing on the page.",
      "avoid_for": "Decks that need visual personality or color-led storytelling — the all-ink palette is intentionally austere.",
      "preview_md": "bold-template-pack/templates/monochrome/preview.md",
      "design_md": "bold-template-pack/templates/monochrome/design.md"
    },
    {
      "slug": "pin-and-paper",
      "name": "Pin & Paper",
      "tagline": "Yellow paper with safety-pin illustrations, ink-blue handwritten Caveat, paper-grain texture.",
      "mood": [
        "crafted",
        "handmade",
        "warm",
        "thoughtful",
        "literary"
      ],
      "tone": [
        "literary",
        "intimate",
        "warm",
        "grounded"
      ],
      "formality": "medium",
      "density": "medium",
      "scheme": "light",
      "best_for": "Anything that should feel hand-crafted, warm, and literary: qualitative research findings, founder reflections, longform brand stories, workshop debriefs. The signature safety-pin illustrations and paper-grain texture make it especially good for any deck — including tech or business — that wants personality and warmth over polish.",
      "avoid_for": "Decks that need to feel digital-native polished or rigorously data-driven — handwritten Caveat is intentionally informal.",
      "preview_md": "bold-template-pack/templates/pin-and-paper/preview.md",
      "design_md": "bold-template-pack/templates/pin-and-paper/design.md"
    },
    {
      "slug": "raw-grid",
      "name": "Raw Grid",
      "tagline": "Neo-brutalist deck with thick borders, offset shadows, and a pink/sage/ink palette.",
      "mood": [
        "raw",
        "punchy",
        "energetic",
        "confident"
      ],
      "tone": [
        "direct",
        "modern",
        "no-nonsense",
        "graphic"
      ],
      "formality": "medium-low",
      "density": "high",
      "scheme": "light",
      "best_for": "Anything that should feel direct and graphic-confident: founder pitches, accelerator demos, brand decks, indie launches, creator portfolios. Strong for stat slides, comparison tables, and process flows. Equally good for tech, research, or finance when the speaker wants the deck to feel scrappy-confident rather than buttoned-up.",
      "avoid_for": "Contexts that need to feel soft, warm, or intentionally quiet — the brutalist borders and offset shadows commit to a graphic voice.",
      "preview_md": "bold-template-pack/templates/raw-grid/preview.md",
      "design_md": "bold-template-pack/templates/raw-grid/design.md"
    },
    {
      "slug": "soft-editorial",
      "name": "Soft Editorial",
      "tagline": "Cormorant Garamond serif on warm paper with sage, blush, and lemon accents.",
      "mood": [
        "literary",
        "elegant",
        "quiet",
        "warm-classical"
      ],
      "tone": [
        "literary",
        "considered",
        "warm",
        "magazine"
      ],
      "formality": "high",
      "density": "low",
      "scheme": "light",
      "best_for": "Anything that should feel literary, elegant, and unhurried: editorial features, longform brand stories, gallery / museum decks, advisory deliverables, wedding / lifestyle media, founder essays. Equally good for tech, research, or business decks that want a Sunday-supplement warmth instead of corporate polish.",
      "avoid_for": "Decks that need visual heat or punch — the warm-paper palette and Cormorant serif are intentionally quiet.",
      "preview_md": "bold-template-pack/templates/soft-editorial/preview.md",
      "design_md": "bold-template-pack/templates/soft-editorial/design.md"
    }
  ]
}